jinja2_mermaid_extension/__init__.py
jinja2_mermaid_extension/base.py
jinja2_mermaid_extension/callback.py
jinja2_mermaid_extension/extension.py
jinja2_mermaid_extension/logger.py
jinja2_mermaid_extension/py.typed
jinja2_mermaid_extension/run.py
jinja2_mermaid_extension/templates/__init__.py
jinja2_mermaid_extension/templates/tikz.tex
jinja2_mermaid_extension-1.5.3.dist-info/LICENSE
jinja2_mermaid_extension-1.5.3.dist-info/METADATA
jinja2_mermaid_extension-1.5.3.dist-info/WHEEL
jinja2_mermaid_extension-1.5.3.dist-info/RECORD
