Metadata-Version: 2.1
Name: jinja2_mermaid_extension
Version: 1.5.3
Summary: A jinja2 block to render a mermaid diagram
Home-page: https://github.com/AdamGagorik/jinja2-mermaid-extension
Author: Adam Gagorik
Author-email: fadam.gagorik@gmail.com
Requires-Python: >=3.12,<4.0
Classifier: Programming Language :: Python :: 3
Classifier: Programming Language :: Python :: 3.12
Requires-Dist: jinja2 (>=3.1.4,<4.0.0)
Requires-Dist: pyyaml (>=6.0.2,<7.0.0)
Project-URL: Documentation, https://AdamGagorik.github.io/jinja2-mermaid-extension/
Project-URL: Repository, https://github.com/AdamGagorik/jinja2-mermaid-extension
